pigguf/__init__.py
pigguf/b.py
pigguf/d.py
pigguf/g.py
pigguf/logo.png
pigguf-0.0.4.dist-info/entry_points.txt
pigguf-0.0.4.dist-info/LICENSE
pigguf-0.0.4.dist-info/METADATA
pigguf-0.0.4.dist-info/WHEEL
pigguf-0.0.4.dist-info/RECORD
