Metadata-Version: 2.3
Name: pigguf
Version: 0.0.4
Summary: gguf kit
Keywords: gguf,pig
Author: gguf
Author-email: info@gguf.us
Classifier: License :: OSI Approved :: MIT License
Classifier: Programming Language :: Python :: 2
Classifier: Programming Language :: Python :: 2.7
Classifier: Programming Language :: Python :: 3
Classifier: Programming Language :: Python :: 3.4
Classifier: Programming Language :: Python :: 3.5
Classifier: Programming Language :: Python :: 3.6
Classifier: Programming Language :: Python :: 3.7
Classifier: Programming Language :: Python :: 3.8
Classifier: Programming Language :: Python :: 3.9
Classifier: Programming Language :: Python :: 3.10
Classifier: Programming Language :: Python :: 3.11
Classifier: Programming Language :: Python :: 3.12
Classifier: Programming Language :: Python :: 3.13
Requires-Dist: gguf-connector (>=2.0.1)
Project-URL: Homepage, https://gguf.org
Project-URL: Repository, https://github.com/gguf-org/pig
